podman/__init__.py
podman/client.py
podman/py.typed
podman/tlsconfig.py
podman/version.py
podman/api/__init__.py
podman/api/adapter_utils.py
podman/api/api_versions.py
podman/api/cached_property.py
podman/api/client.py
podman/api/http_utils.py
podman/api/output_utils.py
podman/api/parse_utils.py
podman/api/path_utils.py
podman/api/ssh.py
podman/api/tar_utils.py
podman/api/uds.py
podman/domain/__init__.py
podman/domain/config.py
podman/domain/containers.py
podman/domain/containers_create.py
podman/domain/containers_manager.py
podman/domain/containers_run.py
podman/domain/events.py
podman/domain/images.py
podman/domain/images_build.py
podman/domain/images_manager.py
podman/domain/ipam.py
podman/domain/json_stream.py
podman/domain/manager.py
podman/domain/manifests.py
podman/domain/networks.py
podman/domain/networks_manager.py
podman/domain/pods.py
podman/domain/pods_manager.py
podman/domain/registry_data.py
podman/domain/secrets.py
podman/domain/system.py
podman/domain/volumes.py
podman/errors/__init__.py
podman/errors/exceptions.py
podman-5.5.0.dist-info/licenses/LICENSE
podman-5.5.0.dist-info/METADATA
podman-5.5.0.dist-info/WHEEL
podman-5.5.0.dist-info/top_level.txt
podman-5.5.0.dist-info/RECORD
