Metadata-Version: 2.4
Name: podman
Version: 5.5.0
Summary: Bindings for Podman RESTful API
Home-page: https://github.com/containers/podman-py
Author: Brent Baude, Urvashi Mohnani
Author-email: Jhon Honce <jhonce@redhat.com>, Nicola Sella <nsella@redhat.com>
License:                                  Apache License
Project-URL: Bug Tracker, https://github.com/containers/podman-py/issues
Project-URL: Homepage, https://github.com/containers/podman-py
Project-URL: Libpod API, https://docs.podman.io/en/latest/_static/api.html
Keywords: libpod,podman
Platform: any
Classifier: Development Status :: 5 - Production/Stable
Classifier: Intended Audience :: Developers
Classifier: License :: OSI Approved :: Apache Software License
Classifier: Operating System :: OS Independent
Classifier: Programming Language :: Python :: 3 :: Only
Classifier: Programming Language :: Python :: 3.9
Classifier: Programming Language :: Python :: 3.10
Classifier: Programming Language :: Python :: 3.11
Classifier: Programming Language :: Python :: 3.12
Classifier: Programming Language :: Python :: 3.13
Classifier: Topic :: Software Development :: Libraries :: Python Modules
Requires-Python: >=3.9
License-File: LICENSE
Requires-Dist: requests>=2.24
Requires-Dist: tomli>=1.2.3; python_version < "3.11"
Requires-Dist: urllib3
Provides-Extra: progress-bar
Requires-Dist: rich>=12.5.1; extra == "progress-bar"
Provides-Extra: docs
Requires-Dist: sphinx; extra == "docs"
Provides-Extra: test
Requires-Dist: coverage; extra == "test"
Requires-Dist: fixtures; extra == "test"
Requires-Dist: pytest; extra == "test"
Requires-Dist: requests-mock; extra == "test"
Requires-Dist: tox; extra == "test"
Dynamic: license-file
